ogidn/__init__.py
ogidn/calibrate.py
ogidn/constants.py
ogidn/income.py
ogidn/input_output.py
ogidn/macro_params.py
ogidn/ogidn_default_parameters.json
ogidn/ogidn_multisector_default_parameters.json
ogidn/utils.py
ogidn/data/002_IFPRI_SAM_IDN_2018_SAM.csv
ogidn-0.0.7.dist-info/LICENSE
ogidn-0.0.7.dist-info/METADATA
ogidn-0.0.7.dist-info/WHEEL
ogidn-0.0.7.dist-info/top_level.txt
ogidn-0.0.7.dist-info/RECORD
