Metadata-Version: 2.1
Name: ogidn
Version: 0.0.7
Summary: Indonesia (IDN) Calibration for OG-Core
Home-page: https://github.com/EAPD-DRB/OG-IDN/
Download-URL: https://github.com/EAPD-DRB/OG-IDN/
Author: Marcelo LaFleur, Richard W. Evans, and Jason DeBacker
License: CC0 1.0 Universal (CC0 1.0) Public Domain Dedication
Project-URL: Issue Tracker, https://github.com/EAPD-DRB/OG-IDN/issues
Keywords: IDN Indonesia calibration of large scale overlapping generations model of fiscal policy
Classifier: Development Status :: 5 - Production/Stable
Classifier: Intended Audience :: Developers
Classifier: Natural Language :: English
Classifier: License :: OSI Approved :: Common Public License
Classifier: Operating System :: POSIX
Classifier: Programming Language :: Python
Classifier: Programming Language :: Python :: 3.11
Classifier: Programming Language :: Python :: 3.12
Classifier: Topic :: Scientific/Engineering :: Information Analysis
Classifier: Topic :: Software Development :: Libraries :: Python Modules
Requires-Python: >=3.7.7, <3.13
License-File: LICENSE
Requires-Dist: numpy
Requires-Dist: psutil
Requires-Dist: scipy>=1.7.1
Requires-Dist: pandas>=1.2.5
Requires-Dist: matplotlib
Requires-Dist: dask>=2.30.0
Requires-Dist: distributed>=2.30.1
Requires-Dist: marshmallow<4.0.0
Requires-Dist: paramtools>=0.15.0
Requires-Dist: requests
Requires-Dist: pandas-datareader
Requires-Dist: xlwt
Requires-Dist: openpyxl>=3.1.2
Requires-Dist: statsmodels
Requires-Dist: linearmodels
Requires-Dist: wheel
Requires-Dist: black
Requires-Dist: linecheck
Requires-Dist: ogcore
